README.md
setup.py
linkedin_search_bot/__init__.py
linkedin_search_bot.egg-info/PKG-INFO
linkedin_search_bot.egg-info/SOURCES.txt
linkedin_search_bot.egg-info/dependency_links.txt
linkedin_search_bot.egg-info/requires.txt
linkedin_search_bot.egg-info/top_level.txt